expressive_regex/__init__.py
expressive_regex/aux_classes.py
expressive_regex/exceptions.py
expressive_regex/expressive.py
expressive_regex/regex_classes.py
expressive_regex-0.4.5.dist-info/LICENSE
expressive_regex-0.4.5.dist-info/WHEEL
expressive_regex-0.4.5.dist-info/METADATA
expressive_regex-0.4.5.dist-info/RECORD
