Metadata-Version: 2.1
Name: expressive-regex
Version: 0.4.5
Summary: 
License: MIT
Author: fsadannn
Author-email: fsadannn@gmail.com
Requires-Python: >=3.6.1,<4
Classifier: License :: OSI Approved :: MIT License
Classifier: Programming Language :: Python :: 3
Classifier: Programming Language :: Python :: 3.7
Classifier: Programming Language :: Python :: 3.8
